LICENSE.txt
MANIFEST.in
README.rst
requirements.txt
setup.cfg
setup.py
logfilter/__init__.py
logfilter/_compact.py
logfilter/common.py
logfilter/logfilter.py
logfilter/ui.py
logfilter.egg-info/PKG-INFO
logfilter.egg-info/SOURCES.txt
logfilter.egg-info/dependency_links.txt
logfilter.egg-info/entry_points.txt
logfilter.egg-info/top_level.txt