Metadata-Version: 1.1
Name: logfilter
Version: 1.0.0
Summary: Poll log files for updates and highlight words based on regexp filters
Home-page: https://bitbucket.org/iamFIREcracker/logfilter
Author: Matteo Landi
Author-email: matteo@matteolandi.net
License: BSD
Download-URL: http://pypi.python.org/pypi/logfilter
Keywords: log,filter,grep,tail
Platform: UNKNOWN
Classifier: Development Status :: 4 - Beta
Classifier: Environment :: Other Environment
Classifier: Intended Audience :: Developers
Classifier: Intended Audience :: Science/Research
Classifier: Intended Audience :: System Administrators
Classifier: License :: OSI Approved :: BSD License
Classifier: Operating System :: OS Independent
Classifier: Programming Language :: Python :: 2.7
Classifier: Programming Language :: Python :: 3.2
Classifier: Topic :: Text Processing :: Filters
Classifier: Topic :: Utilities
